<?xml version="1.0" encoding="us-ascii"?>
<Prefab GenerateHLod="1" Id="e14554ca-e24f-4902-8abd-d37e2a3f4a94">
  <Objects>
    <Object Id="165b8a1a-a4d4-4093-9a01-09542dfbc654" LodRatio="200" Name="element_window_plaster_a-frame_100_001" Pos="-1.39727,-2.566807,1.482474" Prefab="objects\intermediates\elements/window_plaster_a-frame_100.cgf" Rotate="0.7204284,0.6935294,3.591232e-08,-7.754491e-07" Type="Brush" />
    <Object Id="392f6b27-228d-433b-bb24-497b994ca930" LodRatio="200" Name="element_window_cellar_c_002" Pos="3.752527,-1.062731,0.6846693" Prefab="objects\intermediates\elements/window_cellar_c.cgf" Rotate="0.5352229,0.4617338,0.4620453,0.5355861" Type="Brush" />
    <Object Id="39a8f552-bdb9-4b6a-a4a5-b80e1666e6c9" LodRatio="200" Name="element_window_cellar_c_001" Pos="-0.4708081,-2.692966,0.6846696" Prefab="objects\intermediates\elements/window_cellar_c.cgf" Rotate="0.7581106,0.652126,3.082169e-08,2.316368e-09" Type="Brush" />
    <Object Id="65afa499-973a-407a-98fa-607c5d934274" LodRatio="200" Name="element_window_plaster_a-frame_100_003" Pos="0.2638965,2.570083,1.480534" Prefab="objects\intermediates\elements/window_plaster_a-frame_100.cgf" Rotate="7.215558e-07,-8.648733e-08,0.6919696,0.7219267" Type="Brush" />
    <Object Id="a375e133-faad-406d-8347-31e8e3c599d9" LodRatio="200" Name="element_window_plaster_a-frame_100_004" Pos="1.938896,2.570083,1.480534" Prefab="objects\intermediates\elements/window_plaster_a-frame_100.cgf" Rotate="7.215558e-07,-8.648733e-08,0.6919696,0.7219267" Type="Brush" />
    <Object Id="df073ed6-de15-4342-92bd-0e14be4bae98" LodRatio="200" Name="element_window_cellar_c_003" Pos="3.558657,0.3413196,2.08909" Prefab="objects\intermediates\elements/window_cellar_c.cgf" Rotate="0.5146915,0.4856511,0.484878,0.5139349" Type="Brush" />
    <Object Id="e8469b03-1d6d-4faa-9c34-981bd4376ed8" LodRatio="150" Name="granary_d" Prefab="objects/manmade/structures/industrial/granaries/granary_d.cgf" RainOccluder="1" RndFlags="180060000408" Type="Brush" />
    <Object Id="eab02b5e-0bff-4834-b775-6ac8f9bbf850" LodRatio="200" Name="element_window_plaster_a-frame_100_002" Pos="1.630161,-2.566807,1.482473" Prefab="objects\intermediates\elements/window_plaster_a-frame_100.cgf" Rotate="0.7204284,0.6935294,3.591232e-08,-7.754491e-07" Type="Brush" />
    <Object Id="fe149e93-f745-4efb-aec4-f6eee5809e8f" LodRatio="200" Name="element_doorway_plaster_b_001" Pos="-1.638643,1.934935,1.181194" Prefab="objects\intermediates\elements/doorway_plaster_b.cgf" Rotate="0.7071068,0.7071068,-6.181724e-08,6.181724e-08" Type="Brush" />
  </Objects>
</Prefab>