<?xml version="1.0" encoding="us-ascii"?>
<Prefab GenerateHLod="1" Id="b11eeb2b-054d-43c4-b051-247073c54d05">
	<Objects>
		<Object EntityClass="ReflexLight" Id="07e1b861-9ef2-48a3-9fa1-a377a13bae9d" Name="rl_house_1s_3r_e_5" Pos="-1.482178,7.39624,1.995529" Rotate="4.371139e-08,0,0,1" Type="Entity">
			<Properties Radius="5">
				<Options fVerticalClipDistanceDownward="2" fVerticalClipDistanceUpward="1" />
				<Projector fProjectorFov="140" />
				<Shadows nCastShadows="0" />
				<Shape fPlaneHeight="0.28" fPlaneWidth="0.5" fWallThickness="0.23" />
			</Properties>
		</Object>
		<Object ExcludeFromInteriorHLod="1" Id="0dc6580d-a92d-47a6-b7b1-15d88e630c27" LodRatio="70" Name="element_window_timber_a_small_007" Pos="-1.475088,7.141183,1.99799" Prefab="objects\intermediates\elements/window_timber_a_small.cgf" Rotate="0.002817959,0.00248757,0.7093551,-0.7048413" Type="Brush" />
		<Object Id="13ee50fc-ebbc-4f1e-8eab-ec15d498053e" Name="Door/door_village_left8" Pos="-1.837219,-1.367126,0.01179933" PrefabTemplate="be4e8919-a517-4e19-929f-4a7b5e771e0e" PrefabTemplateName="Door/door_village_left" Type="Prefab" />
		<Object ExcludeFromInteriorHLod="1" Id="1509a860-f861-4a35-9cf5-5ae822c204c5" LodRatio="70" Name="element_doorway_timber_a2_001" Pos="-3.003462,1.909162,0.08909225" Prefab="objects\intermediates\elements/doorway_timber_a2.cgf" Rotate="-0.4999999,-0.5,0.5,0.5000001" Type="Brush" />
		<Object EntityClass="ReflexLight" Id="15d04abf-dd4a-4d70-9777-3e31a5298be1" Name="rl_house_1s_3r_e_8" Pos="1.481201,7.38916,1.991821" Rotate="4.371139e-08,0,0,1" Type="Entity">
			<Properties Radius="5">
				<Options fVerticalClipDistanceDownward="2" fVerticalClipDistanceUpward="1" />
				<Projector fProjectorFov="140" />
				<Shadows nCastShadows="0" />
				<Shape fPlaneHeight="0.28" fPlaneWidth="0.5" fWallThickness="0.23" />
			</Properties>
		</Object>
		<Object Id="19f27fa2-a600-4a2d-9c1d-1c82d5827da0" Name="Door/door_village_left6" Pos="-2.753357,1.276855,0.04767609" PrefabTemplate="be4e8919-a517-4e19-929f-4a7b5e771e0e" PrefabTemplateName="Door/door_village_left" Rotate="0.7071068,0,0,0.7071068" Type="Prefab" />
		<Object Id="20030c04-1640-4d81-a1d2-b4048b59861d" LodRatio="70" Name="element_doorway_timber_a2_002" Pos="-1.374707,3.019939,0.0101622" Prefab="objects\intermediates\elements/doorway_timber_a2.cgf" Rotate="0.7071061,0.7071065,0.0007736276,-0.0007736367" Type="Brush" />
		<Object Id="2089b391-aefb-4b6c-b13d-1a936a629aca" LodRatio="70" Name="element_window_timber_a_small_005" Pos="2.742646,1.045524,2.089791" Prefab="objects\intermediates\elements/window_timber_a_small.cgf" Rotate="-0.4964055,0.5033488,0.4998308,-0.5003906" Type="Brush" />
		<Object EntityClass="ReflexLight" Id="2627f838-d1b0-40a6-bdbe-bd0353b2d46a" Name="rl_house_1s_3r_e_2" Pos="-1.179199,-7.574097,1.468758" Type="Entity">
			<Properties Radius="7">
				<Options fVerticalClipDistanceDownward="1.5" fVerticalClipDistanceUpward="2" />
				<Projector fProjectorFov="140" />
				<Shape fPlaneHeight="0.6" fPlaneWidth="0.55" fWallThickness="0.23" />
			</Properties>
		</Object>
		<Object EntityClass="ClipVolume" Id="2e748ac7-7556-4f3c-9021-24330414281a" Name="ClipVolume151" SourceGeometry="objects/manmade/structures/living/houses/cv_house_1s_3r_e_1.cgf" Type="ClipVolume" />
		<Object EntityClass="ReflexLight" Id="465c7813-eaea-4750-ba41-21ae7decdd6c" Name="rl_house_1s_3r_e_3" Pos="-2.979248,-5.789307,1.349098" Rotate="0.7071068,0,0,-0.7071068" Type="Entity">
			<Properties Radius="6">
				<Options fVerticalClipDistanceDownward="1.4" fVerticalClipDistanceUpward="2.5" />
				<Projector fProjectorFov="140" />
				<Shape fPlaneHeight="0.6" fPlaneWidth="0.55" fWallThickness="0.23" />
			</Properties>
		</Object>
		<Object ExcludeFromInteriorHLod="1" Id="46ad3b63-b81e-4a08-a957-17f9385f4a48" LodRatio="70" Name="element_window_timber_a_big-half-white_004" Pos="-3.003462,-3.233166,1.350415" Prefab="objects\intermediates\elements/window_timber_a_big-half-white.cgf" Rotate="-0.4982628,0.5017312,0.4982629,-0.5017311" Scale="0.8437898,0.98107,1" Type="Brush" />
		<Object DisplayFilled="1" EntityClass="TriggerArea" Height="8" Id="4ab53891-ba79-49f7-9bab-afde61e18b58" Name="SmartArea16" Pos="2.842041,7.375854,-0.09999847" Type="WH_TriggerArea">
			<Properties Label="private; personal; interior" />
			<EntityLinks>
				<Link DebugTargetName="outPort_homeEquipment" Name="home_equipment" TargetId="f12e07e6-89ee-4dbf-b15a-e20e72815d59" />
			</EntityLinks>
			<Points>
				<Point Pos="0,0,0" />
				<Point Pos="-0.008361816,-14.87164,-0.1" />
				<Point Pos="-5.798126,-14.76312,-0.1" />
				<Point Pos="-5.737701,-0.1091919,-0.1" />
			</Points>
			<SoundData Floor="0" Roof="0" Side1="0" Side2="0" Side3="0" Side4="0" />
		</Object>
		<Object EntityClass="ReflexLight" Id="4e117ab3-3799-404c-a54d-5b1151f32527" Name="rl_house_1s_3r_e_4" Pos="-2.982666,-3.226807,1.337219" Rotate="0.7071068,0,0,-0.7071068" Type="Entity">
			<Properties Radius="6">
				<Options fVerticalClipDistanceDownward="1.4" fVerticalClipDistanceUpward="2.5" />
				<Projector fProjectorFov="140" />
				<Shape fPlaneHeight="0.6" fPlaneWidth="0.55" fWallThickness="0.23" />
			</Properties>
		</Object>
		<Object EntityClass="ReflexLight" Id="52b3ab6f-a15e-4152-a29b-039049e3c0ff" Name="rl_house_1s_3r_e_11" Pos="2.996826,1.029663,2.08477" Rotate="0.7071068,0,0,0.7071068" Type="Entity">
			<Properties Radius="4">
				<Options fVerticalClipDistanceDownward="2.2" fVerticalClipDistanceUpward="2" />
				<Projector fProjectorFov="140" />
				<Shadows nCastShadows="0" />
				<Shape fPlaneHeight="0.28" fPlaneWidth="0.45" fWallThickness="0.23" />
			</Properties>
		</Object>
		<Object EntityClass="ClipVolume" Id="56ec86a2-e002-4f2c-9bc5-acf26ea7f102" Name="ClipVolume153" SourceGeometry="objects/manmade/structures/living/houses/cv_house_1s_3r_e_3.cgf" Type="ClipVolume" />
		<Object EntityClass="ReflexLight" Id="60c89301-b867-4a58-a0ad-dd6777eb337b" Name="rl_house_1s_3r_e_1" Pos="1.114502,-7.570312,1.478561" Type="Entity">
			<Properties Radius="7">
				<Options fVerticalClipDistanceDownward="1.5" fVerticalClipDistanceUpward="2" />
				<Projector fProjectorFov="140" />
				<Shape fPlaneHeight="0.6" fPlaneWidth="0.55" fWallThickness="0.23" />
			</Properties>
		</Object>
		<Object ExcludeFromInteriorHLod="1" Id="760ae514-f46d-4b52-9771-dc15b002e1eb" LodRatio="70" Name="element_window_timber_a_big-half-white_003" Pos="-3.003462,-5.781271,1.344537" Prefab="objects\intermediates\elements/window_timber_a_big-half-white.cgf" Rotate="0.5024269,-0.4975612,-0.502427,0.4975612" Scale="0.8329599,0.96848,1" Type="Brush" />
		<Object EntityClass="ReflexLight" Id="926ff9b2-a528-40f4-b696-1fce68a2a24d" Name="rl_house_1s_3r_e_7" Pos="0.02490234,-7.590576,2.981995" Type="Entity">
			<Properties Radius="4">
				<Options fVerticalClipDistanceDownward="3" fVerticalClipDistanceUpward="1" />
				<Projector fProjectorFov="140" />
				<Shadows nCastShadows="0" />
				<Shape fPlaneHeight="0.27" fPlaneWidth="0.42" fWallThickness="0.23" />
			</Properties>
		</Object>
		<Object Id="9c45cd65-ae75-4b74-b296-a0689d4f18c5" Name="Door/door_village_right5" Pos="0.8798828,3.273804,0.01258087" PrefabTemplate="17c3f8d9-a46f-4dc9-854f-49609f7457a2" PrefabTemplateName="Door/door_village_right" Rotate="-4.371139e-08,0,0,1" Type="Prefab" />
		<Object EntityClass="PrefabPort" Id="9da3e748-cb64-4880-94cc-ae8b96a281bd" Name="port_crime" Pos="0.07556152,-4.219727,7.360237" Type="Entity">
			<EntityLinks>
				<Link DebugTargetName="SmartArea16" TargetId="4ab53891-ba79-49f7-9bab-afde61e18b58" />
			</EntityLinks>
		</Object>
		<Object EntityClass="FogVolume" Id="a2a9c4b9-c8a3-4451-9e59-a0876af02843" Name="fog_interior14" Pos="0,-0.09154129,2.891797" Type="Entity" ViewDistRatio="1">
			<Properties color_Color="0.48515,0.371238,0.258183" color_Emission="0.838799,0.672443,0.187821" eiVolumeType="1" fHDRDynamic="1" GlobalDensity="0.15" RampEnd="0">
				<Size x="5.9" y="14.9" z="8" />
			</Properties>
		</Object>
		<Object Id="b8cf9c94-2715-4e14-80fd-83df79844f33" LodRatio="50" Name="house_1s_3r_e" Prefab="objects\manmade\structures\living\houses\house_1s_3r_e.cgf" RainOccluder="1" RndFlags="180060000408" Type="Brush" />
		<Object ExcludeFromInteriorHLod="1" Id="c13fd291-ec44-4686-8a8d-f464e7001ed4" LodRatio="70" Name="element_window_timber_a_big-half-white_002" Pos="1.12064,-7.608891,1.477515" Prefab="objects\intermediates\elements/window_timber_a_big-half-white.cgf" Rotate="-0.0004857263,-0.0004857264,-0.7071066,0.7071066" Scale="0.81702,1.04506,0.9999998" Type="Brush" />
		<Object EntityClass="ClipVolume" Id="c363e3b2-9c59-495b-94df-a5979e9858c4" Name="ClipVolume154" SourceGeometry="objects/manmade/structures/living/houses/cv_house_1s_3r_e_4.cgf" Type="ClipVolume" />
		<Object EntityClass="ReflexLight" Id="c707c464-1619-457c-8ef0-c04d8ce63900" Name="rl_house_1s_3r_e_6" Pos="-2.94873,0.02539062,1.347137" Rotate="0.7071068,0,0,-0.7071068" Type="Entity">
			<Properties Radius="6">
				<Options fVerticalClipDistanceDownward="1.4" fVerticalClipDistanceUpward="2" />
				<Projector fProjectorFov="140" />
				<Shape fPlaneHeight="0.53" fPlaneWidth="0.48" fWallThickness="0.23" />
			</Properties>
		</Object>
		<Object Id="cb06fac1-ee80-4e87-80b2-533ae18f97f6" Name="Door/door_village_left7" Pos="-0.740509,3.259949,0.01416779" PrefabTemplate="be4e8919-a517-4e19-929f-4a7b5e771e0e" PrefabTemplateName="Door/door_village_left" Rotate="2.793968e-09,0,0,1" Type="Prefab" />
		<Object Id="cca417aa-db9b-42f0-a7ea-5020c1e88193" LodRatio="70" Name="element_doorway_timber_a-half-white_001" Pos="-1.219631,-1.115995,0.009348908" Prefab="objects\intermediates\elements/doorway_timber_a-half-white.cgf" Rotate="-0.001217615,0.001217616,0.7071058,0.7071057" Type="Brush" />
		<Object EntityClass="ClipVolume" Id="d317fc39-7592-4f99-a82a-dc76a421d39a" Name="ClipVolume152" SourceGeometry="objects/manmade/structures/living/houses/cv_house_1s_3r_e_2.cgf" Type="ClipVolume" />
		<Object Id="d7356e13-6f17-48a5-9d10-e5232a8c1f50" LodRatio="70" Name="element_doorway_timber_a2_003" Pos="1.443686,3.019939,0.0101622" Prefab="objects\intermediates\elements/doorway_timber_a2.cgf" Rotate="0.7071061,0.7071065,0.0007736276,-0.0007736367" Type="Brush" />
		<Object EntityClass="EnvironmentLight" Id="e69cf922-82c1-43b4-b23a-23a732cc9275" Name="envprobe_house_1s_3r_e" Pos="-0.006103516,-0.1118164,3.464653" Type="EnvironmentProbe">
			<Properties BoxSizeX="5.6" BoxSizeY="14.8" BoxSizeZ="7" GenOffsetY="-3" GenOffsetZ="-2">
				<Options fAttenuationFalloffMax="0" fGiBiasMultiplier="0.1" />
			</Properties>
		</Object>
		<Object ExcludeFromInteriorHLod="1" Id="f0837e51-6350-4030-8bbf-8fdc91201fbf" LodRatio="70" Name="element_window_timber_a_small_006" Pos="0.03485107,-7.608891,2.974404" Prefab="objects\intermediates\elements/window_timber_a_small.cgf" Rotate="0.7071068,0.7071068,0,0" Type="Brush" />
		<Object ExcludeFromInteriorHLod="1" Id="f0ef569f-8923-487f-8a84-6f6c688cf1fe" LodRatio="70" Name="element_window_timber_a_big2_001" Pos="-3.008032,0.0257196,1.341873" Prefab="objects\intermediates\elements/window_timber_a_big2.cgf" Rotate="-0.4995146,-0.4995146,0.5004849,0.5004849" Scale="0.7391064,1,1" Type="Brush" />
		<Object EntityClass="PrefabPort" Id="f12e07e6-89ee-4dbf-b15a-e20e72815d59" Name="outPort_homeEquipment" Pos="0.07556152,-3.513672,7.360237" Type="Entity">
			<Properties esPrefabPort_Type="Out" />
		</Object>
		<Object ExcludeFromInteriorHLod="1" Id="f1f7e095-4359-42fe-9ea9-b338511e75dc" LodRatio="70" Name="element_window_timber_a_big-half-white_001" Pos="-1.178467,-7.608891,1.468025" Prefab="objects\intermediates\elements/window_timber_a_big-half-white.cgf" Rotate="0.0004718941,0.00047189,0.7071066,-0.7071066" Scale="0.81702,1.04506,0.9999999" Type="Brush" />
		<Object ExcludeFromInteriorHLod="1" Id="f6b599cf-4aa8-4621-90b8-77dda8b77c4b" LodRatio="70" Name="element_window_timber_a_small_002" Pos="1.463821,7.141183,1.99799" Prefab="objects\intermediates\elements/window_timber_a_small.cgf" Rotate="0.002817959,0.00248757,0.7093551,-0.7048413" Type="Brush" />
		<Object EntityClass="ReflexLight" Id="fc19b486-9cde-4bbb-b1ea-72bab32411cf" Name="rl_door_house_1s_3r_e_1" Pos="-2.794189,1.884155,1.139191" Rotate="0.7071068,0,0,-0.7071068" Type="Entity">
			<Properties Radius="7">
				<Options fVerticalClipDistanceDownward="1.1" fVerticalClipDistanceUpward="3.5" />
				<Projector fProjectorFov="170" fProjectorNearPlane="-0.1" />
				<Shadows nCastShadows="1" />
				<Shape fFadeInRadius="1" fPlaneHeight="2" fWallThickness="0.1" />
			</Properties>
		</Object>
	</Objects>
	<NestedLinks>
		<Link Name="crime_door[type($enum:crime_doorKind.entrance)]" SourceDebugName="SmartArea16" SourceId="4ab53891-ba79-49f7-9bab-afde61e18b58" SourcePath="" TargetDebugName="PrefabRoot" TargetId="5cd31374-ac35-4af6-93d1-5a3102d2117c" TargetPath="19f27fa2-a600-4a2d-9c1d-1c82d5827da0" />
		<Link Name="crime_door[type($enum:crime_doorKind.basic)]" SourceDebugName="SmartArea16" SourceId="4ab53891-ba79-49f7-9bab-afde61e18b58" SourcePath="" TargetDebugName="PrefabRoot" TargetId="5cd31374-ac35-4af6-93d1-5a3102d2117c" TargetPath="cb06fac1-ee80-4e87-80b2-533ae18f97f6" />
		<Link Name="crime_door[type($enum:crime_doorKind.basic)]" SourceDebugName="SmartArea16" SourceId="4ab53891-ba79-49f7-9bab-afde61e18b58" SourcePath="" TargetDebugName="PrefabRoot" TargetId="14beb9bd-e633-44c8-828a-fb6f9a5d5793" TargetPath="9c45cd65-ae75-4b74-b296-a0689d4f18c5" />
		<Link Name="crime_door[type($enum:crime_doorKind.basic)]" SourceDebugName="SmartArea16" SourceId="4ab53891-ba79-49f7-9bab-afde61e18b58" SourcePath="" TargetDebugName="PrefabRoot" TargetId="5cd31374-ac35-4af6-93d1-5a3102d2117c" TargetPath="13ee50fc-ebbc-4f1e-8eab-ec15d498053e" />
	</NestedLinks>
</Prefab>