<?xml version="1.0" encoding="us-ascii"?>
<Prefab Id="bad22e6e-32ed-4c2a-9597-668243bb0724">
	<Tags>
		<Tag>ignore</Tag>
	</Tags>
	<Objects>
		<Object EntityClass="ItemSlot" Id="1001b951-43b4-4850-bf49-93e7786801ae" Name="HammerSlot" NoStaticDecals="1" Pos="-0.3168335,-2.37291,0.768158" Rotate="0.07532642,0.6859865,-0.06570482,0.7207159" Type="Entity">
			<Properties bOwnedByHome="0" guidItemClassId="0502824d-a654-4471-9978-c1624860dde1" />
		</Object>
		<Object EntityClass="ParticleEffect" Id="15bc8904-a9f8-4c66-aa6c-891391172ab5" Name="professions.blacksmith.burning_iron4" Pos="5.277225,-2.390701,0.4750862" Rotate="0.3420202,0,0,0.9396926" Type="ParticleEntity">
			<Properties bActive="0" bPrime="0" ParticleEffect="professions.blacksmith.burning_iron" />
		</Object>
		<Object EntityClass="PrefabPort" Id="15c39101-83c1-4069-ab27-11a2d892df02" Name="FreeSpotForPlayerPort" Pos="1.256535,-0.5167084,1.200001" Type="Entity">
			<Properties esForwardedLinkName="Target" esPrefabPort_Type="Out" />
		</Object>
		<Object EntityClass="ParticleEffect" Id="17c48eea-9acc-4573-96ad-e8a15f11e57f" Name="hardening_particle" Pos="1.790604,-1.712479,0.4834595" Rotate="0.7071067,0.7071068,0,0" Type="ParticleEntity">
			<Properties bActive="0" ParticleEffect="professions.blacksmith.hardening" />
		</Object>
		<Object EntityClass="SchedulerHub" Id="1e0d791e-8398-41e2-9aac-1abec9c17d6d" Name="hub_2" Pos="-0.6097527,-1.297211,0.8990593" Type="Entity">
			<EntityLinks>
				<Link DebugTargetName="smartObjectHolder" Name="_1,use" TargetId="de2befbb-d562-4123-a0b9-6e3b8a8cda0b" />
				<Link DebugTargetName="Shop4" Name="#OpenShop[blacksmith]" TargetId="f48b243b-dc66-4101-be77-d5d7cb357a45" />
				<Link DebugTargetName="outPort_area" Name="#ChangeAreaLabel[blacksmith,+antitrespass] " TargetId="f8efbc6b-abc2-482a-aa37-c8fd522c0f44" />
				<Link DebugTargetName="outPort_area" Name="#ChangeAreaLabel[blacksmith,+publicServiceTrespassOverride] " TargetId="f8efbc6b-abc2-482a-aa37-c8fd522c0f44" />
				<Link DebugTargetName="hub_2" Name="#AddMetaRole[blacksmith,REPAIRMAN]" TargetId="1e0d791e-8398-41e2-9aac-1abec9c17d6d" />
				<Link DebugTargetName="hub_2" Name="#AddContext[blacksmith,shop_sellerReadyToSell]" TargetId="1e0d791e-8398-41e2-9aac-1abec9c17d6d" />
			</EntityLinks>
		</Object>
		<Object EntityClass="ParticleEffect" Id="1e679e72-e8e5-47c6-acc8-d7373416fde6" Name="professions.blacksmith.burning_iron1_2" Pos="4.148682,-1.458923,0.4750862" Rotate="0.3420202,0,0,0.9396926" Type="ParticleEntity">
			<Properties bActive="0" bPrime="0" ParticleEffect="professions.blacksmith.burning_iron_sword" />
		</Object>
		<Object EntityClass="PrefabPort" Id="1e99e951-ce7b-4b50-b1ba-5c8504f9005a" Name="port_use" Pos="0.03191757,-1.297211,2.103527" Type="Entity">
			<EntityLinks>
				<Link DebugTargetName="hub" TargetId="7c15f75b-e5bb-400c-bde0-eb3fd8c295ca" />
			</EntityLinks>
		</Object>
		<Object EntityClass="TagPoint" Id="1ee4dc09-8ac3-4775-82fc-7ee42c284050" Name="SmitheryAlignPoint" Rotate="0.9999619,0,0,0.008726535" Type="TagPoint" />
		<Object EntityClass="GhostDummy" Id="1ef5f66c-3e48-4547-ade7-c1557ebb7681" Name="blacksmith_sword_grab_to_insert1" Rotate="0.9999619,0,0,0.008726479" Type="Entity">
			<Properties object_Model="Objects/intermediates/poses/blacksmith_sword_grab_to_insert.cgf" />
		</Object>
		<Object EntityClass="ParticleEffect" Id="215e6b7a-4f14-4a9b-94c0-789cce0eb4de" Name="hammering_hit_particle" Pos="0.09407806,-2.428482,0.8151588" Rotate="0.7071067,0.7071068,0,0" Type="ParticleEntity">
			<Properties bActive="0" bPrime="0" ParticleEffect="professions.blacksmith.hammering_hit" />
		</Object>
		<Object EntityClass="TagPoint" Id="2758c10e-95ca-4222-bb9a-69ea93c43ec9" Name="TagPoint1" Pos="-1.265406,0.4755707,-1.100956" Type="TagPoint">
			<EntityLinks>
				<Link DebugTargetName="swordSlot" TargetId="70f69dda-e963-4773-ae5c-389818b8f7f5" />
			</EntityLinks>
		</Object>
		<Object EntityClass="GhostDummy" Id="29e73cd5-ceaf-4067-92db-1e070cb28201" Name="blacksmith_sword_heating_to_forging1" Rotate="0.9999619,0,0,0.008726479" Type="Entity">
			<Properties object_Model="Objects/intermediates/poses/blacksmith_sword_heating_to_forging.cgf" />
		</Object>
		<Object EntityClass="PrefabPort" Id="2f742e86-4f15-4bbd-ab1f-980bf5eef4af" Name="port_ownership" Pos="-1.448486,-2.476562,-0.0423584" Type="Entity">
			<EntityLinks>
				<Link DebugTargetName="Shop4" Name="owner" TargetId="f48b243b-dc66-4101-be77-d5d7cb357a45" />
			</EntityLinks>
		</Object>
		<Object EntityClass="ItemSlot" Id="318b3d1b-86ec-4d41-8861-3ba3ca527148" Name="TongsSlot" NoStaticDecals="1" Pos="2.141502,-1.154099,0.7028008" Rotate="0.1613911,-0.3242939,-0.5981117,0.7148768" Type="Entity">
			<Properties bOwnedByHome="0" guidItemClassId="f22b7bb9-fa73-4aa1-92e6-3943e2be7e69" />
		</Object>
		<Object EntityClass="PrefabPort" Id="354dce20-c79f-4e9d-b5ce-8a9674c1b8aa" Name="CoalPort" Pos="0.3049049,-0.7823334,0.2000008" Type="Entity">
			<Properties esForwardedLinkName="Source" esPrefabPort_Type="Out" />
		</Object>
		<Object EntityClass="ParticleEffect" Id="3cb351cd-8740-4b71-a11c-e82539e88eee" Name="professions.blacksmith.burning_iron3" Pos="4.973026,-2.085709,0.4750862" Rotate="0.3420202,0,0,0.9396926" Type="ParticleEntity">
			<Properties bActive="0" bPrime="0" ParticleEffect="professions.blacksmith.burning_iron" />
		</Object>
		<Object EntityClass="GhostDummy" Id="3cd99379-9cbb-41b7-b4cf-1b7e9b468700" Name="blacksmith_sword_heating1" Rotate="0.9999619,0,0,0.008726479" Type="Entity">
			<Properties object_Model="Objects/intermediates/poses/blacksmith_sword_heating.cgf" />
		</Object>
		<Object EntityClass="ItemSlot" Id="54a3e628-af7d-46a7-8e05-37b8a9d10dd1" Name="swordHeatingPlaceSlot" Pos="-0.4862,-0.3415,0.6754" Rotate="-0.01308694,0.02741546,0.7019362,0.7115917" Type="Entity">
			<Properties bOwnedByHome="0" bSpawnOnStart="0" guidItemClassId="4ce95b2e-d0ed-439a-a705-ab051c499927" />
		</Object>
		<Object EntityClass="ParticleEffect" Id="5a6c1454-907d-4176-a7b9-afb4fd186f4e" Name="forge_particle" Pos="-0.8806152,0.296875,0.7615356" Rotate="0.7071069,0.7071067,0,0" Scale="0.612498,0.612498,0.612498" Type="ParticleEntity">
			<Properties bPrime="0" ParticleEffect="professions.blacksmith.forge_fire" />
		</Object>
		<Object EntityClass="Smithery" Id="60aca2b1-6373-4fc5-a07b-11b71c5a49d0" Material="materials/special/nodraw" Name="Smithery" Pos="0.04626465,-2.705902,-0.1784401" Rotate="0.8539892,0,0,0.5202907" Scale="0.7,0.7,0.7" Type="Entity">
			<Properties object_Model="objects/special/primitive_cylinder.cgf" />
			<EntityLinks>
				<Link DebugTargetName="TongsSlot" Name="tongs" TargetId="318b3d1b-86ec-4d41-8861-3ba3ca527148" />
				<Link DebugTargetName="HammerSlot" Name="hammer" TargetId="1001b951-43b4-4850-bf49-93e7786801ae" />
				<Link DebugTargetName="SmitheryAlignPoint" Name="alignment" TargetId="1ee4dc09-8ac3-4775-82fc-7ee42c284050" />
				<Link DebugTargetName="professions.blacksmith.burning_iron1" Name="qualityLoss_sword_00" TargetId="7906ed1d-d9e4-418b-94ac-2ec2fde99ccb" />
				<Link DebugTargetName="professions.blacksmith.burning_iron2" Name="qualityLoss_00" TargetId="ea482467-3c1d-4e86-a66c-9206a82d8cdb" />
				<Link DebugTargetName="professions.blacksmith.burning_iron3" Name="qualityLoss_01" TargetId="3cb351cd-8740-4b71-a11c-e82539e88eee" />
				<Link DebugTargetName="professions.blacksmith.burning_iron4" Name="qualityLoss_02" TargetId="15bc8904-a9f8-4c66-aa6c-891391172ab5" />
				<Link DebugTargetName="hammering_hit_particle" Name="anvilParticles" TargetId="215e6b7a-4f14-4a9b-94c0-789cce0eb4de" />
				<Link DebugTargetName="hardening_particle" Name="hardeningParticles" TargetId="17c48eea-9acc-4573-96ad-e8a15f11e57f" />
				<Link DebugTargetName="forge_particle" Name="forgeHeatingParticles" TargetId="5a6c1454-907d-4176-a7b9-afb4fd186f4e" />
				<Link DebugTargetName="light_forge" Name="forgeLight" TargetId="928e1014-99a8-4284-9edf-ed9adb113a6a" />
				<Link DebugTargetName="forge_particle_big" Name="forgeStartParticles" TargetId="e6e33159-cc4c-4a57-aafc-9936b64fe205" />
				<Link DebugTargetName="ForgeBagPort" Name="forgeBag" TargetId="96557a57-7e05-40ca-9c67-4f2fe9b9fd6a" />
				<Link DebugTargetName="CoalPort" Name="forgeCoal" TargetId="354dce20-c79f-4e9d-b5ce-8a9674c1b8aa" />
				<Link DebugTargetName="smartObjectHolder" TargetId="de2befbb-d562-4123-a0b9-6e3b8a8cda0b" />
				<Link DebugTargetName="professions.blacksmith.burning_iron1_2_2" Name="qualityLoss_sword_01" TargetId="8f42043f-30d6-4d4d-9994-c60be8a055a6" />
				<Link DebugTargetName="professions.blacksmith.burning_iron1_2" Name="qualityLoss_sword_02" TargetId="1e679e72-e8e5-47c6-acc8-d7373416fde6" />
			</EntityLinks>
		</Object>
		<Object EntityClass="ItemSlot" Id="70f69dda-e963-4773-ae5c-389818b8f7f5" Name="swordSlot" Pos="2.3749,-1.2376,1.1253" Rotate="-0.0537808,0.2286338,0.9704366,-0.0555612" Type="Entity">
			<Properties bOwnedByHome="0" guidItemClassId="4ce95b2e-d0ed-439a-a705-ab051c499927" />
		</Object>
		<Object EntityClass="ParticleEffect" Id="7906ed1d-d9e4-418b-94ac-2ec2fde99ccb" Name="professions.blacksmith.burning_iron1" Pos="3.320007,-0.7635803,0.4750862" Rotate="0.3420202,0,0,0.9396926" Type="ParticleEntity">
			<Properties bActive="0" bPrime="0" ParticleEffect="professions.blacksmith.burning_iron_sword" />
		</Object>
		<Object EntityClass="SchedulerHub" Id="7c15f75b-e5bb-400c-bde0-eb3fd8c295ca" Name="hub" Pos="0.04636383,-1.297211,0.8990593" Type="Entity">
			<EntityLinks>
				<Link DebugTargetName="hub_2" Name="_|blacksmith" TargetId="1e0d791e-8398-41e2-9aac-1abec9c17d6d" />
			</EntityLinks>
		</Object>
		<Object Id="8f2558c6-e8a6-4fc4-a146-d4d1cb00ce5e" Name="Chest/chest4" Pos="-1.332348,-5.023285,0" PrefabTemplate="9731b7cc-034d-44c9-b094-c646cfb03498" PrefabTemplateName="Chest/chest" Type="Prefab" />
		<Object EntityClass="ParticleEffect" Id="8f42043f-30d6-4d4d-9994-c60be8a055a6" Name="professions.blacksmith.burning_iron1_2_2" Pos="3.744995,-1.120178,0.4750862" Rotate="0.3420202,0,0,0.9396926" Type="ParticleEntity">
			<Properties bActive="0" bPrime="0" ParticleEffect="professions.blacksmith.burning_iron_sword" />
		</Object>
		<Object EntityClass="Light" Id="928e1014-99a8-4284-9edf-ed9adb113a6a" Name="light_forge" Pos="-0.7329063,0.5848541,1.046997" Type="Entity">
			<Properties fAttenuationBulbSize="0.4" Radius="5">
				<Color clrDiffuse="0.730461,0.226966,0.0612461" fDiffuseMultiplier="0.02" />
				<Options fVerticalClipDistanceDownward="3" fVerticalClipDistanceUpward="11" />
				<Shadows nCastShadows="2" />
			</Properties>
		</Object>
		<Object EntityClass="PrefabPort" Id="96557a57-7e05-40ca-9c67-4f2fe9b9fd6a" Name="ForgeBagPort" Pos="1.256535,-0.5167084,0.2000008" Type="Entity">
			<Properties esForwardedLinkName="Source" esPrefabPort_Type="Out" />
		</Object>
		<Object EntityClass="PrefabPort" Id="a628ef6c-7722-4565-992b-6830bee6320f" Name="port_shopkeeper" Pos="-1.448486,-2.871582,-0.0423584" Type="Entity">
			<EntityLinks>
				<Link DebugTargetName="Shop4" Name="shopKeeper" TargetId="f48b243b-dc66-4101-be77-d5d7cb357a45" />
			</EntityLinks>
		</Object>
		<Object Id="aa7196bb-1441-43cf-ba6f-014d8595ba15" Name="water_container" Pos="1.791855,-1.701996,0" Prefab="objects\manmade\task_specific_props\metal_industry\smithing\water_container.cgf" Rotate="0.7831511,0,0,0.6218315" Type="Brush">
			<CollisionFiltering>
				<Type gcc_interactive="1" />
			</CollisionFiltering>
		</Object>
		<Object Id="b4b7fc16-6268-4c48-8fa2-a9c202150698" LodRatio="255" Name="barrel_forging1" Pos="2.259705,-1.341202,0" Prefab="Objects/manmade/task_specific_props/metal_industry/smithing/barrel_forging.cgf" Rotate="-0.1968317,0,0,0.9804373" Type="Brush" ViewDistRatio="60">
			<CollisionFiltering>
				<Type gcc_interactive="1" />
			</CollisionFiltering>
		</Object>
		<Object Id="c05ae758-c195-4cfc-a28a-81e734eb99e5" Name="anvil" Pos="0.05970383,-2.735703,-0.1090736" Prefab="objects\manmade\task_specific_props\metal_industry\smithing\anvil.cgf" Rotate="0.7985829,0,0,0.6018848" Type="Brush">
			<CollisionFiltering>
				<Type gcc_interactive="1" />
			</CollisionFiltering>
		</Object>
		<Object Id="d3a040a4-4123-4894-bc4c-e0d23f47e9cb" Name="Idle/leaningSpot_blacksmith" Pos="2.320118,-4.312378,0" PrefabTemplate="b28cb2ab-e1fd-4e17-92d9-5b4892c6467c" PrefabTemplateName="Idle/leaningSpot_blacksmith" Type="Prefab" />
		<Object EntityClass="ItemSlot" Id="ddae38e9-ffdb-4f22-a5c5-f69f28f56b06" Name="swordHeatingSlot" Pos="-0.8232,-0.5695,0.643" Rotate="0.7231919,-0.6897936,0.03410521,0.003891194" Type="Entity">
			<Properties bOwnedByHome="0" bSpawnOnStart="0" guidItemClassId="4ce95b2e-d0ed-439a-a705-ab051c499927" />
		</Object>
		<Object EntityClass="SmartObjectHolder" Id="de2befbb-d562-4123-a0b9-6e3b8a8cda0b" Name="smartObjectHolder" Type="Entity">
			<Properties guidSmartObjectType="a7daaa9f-8424-430d-80a6-e7996aed85a3" soclass_SmartObjectHelpers="Blacksmith" />
			<EntityLinks>
				<Link DebugTargetName="swordSlot" Name="swordSlot" TargetId="70f69dda-e963-4773-ae5c-389818b8f7f5" />
				<Link DebugTargetName="swordHeatingSlot" Name="swordHeatingSlot" TargetId="ddae38e9-ffdb-4f22-a5c5-f69f28f56b06" />
				<Link DebugTargetName="HammerSlot" Name="hammerSlot" TargetId="1001b951-43b4-4850-bf49-93e7786801ae" />
				<Link DebugTargetName="ForgeBagPort" Name="forgeBag" TargetId="96557a57-7e05-40ca-9c67-4f2fe9b9fd6a" />
				<Link DebugTargetName="swordHeatingPlaceSlot" Name="swordHeatingPlaceSlot" TargetId="54a3e628-af7d-46a7-8e05-37b8a9d10dd1" />
				<Link DebugTargetName="FreeSpotForPlayerPort" TargetId="15c39101-83c1-4069-ab27-11a2d892df02" />
				<Link DebugTargetName="TagPoint1" Name="schedulerReservedItem[&apos;use&apos;,&apos;blacksmith_sword&apos;]" TargetId="2758c10e-95ca-4222-bb9a-69ea93c43ec9" />
				<Link DebugTargetName="smartObjectHolder" Name="+Soil[blacksmith,4]" TargetId="de2befbb-d562-4123-a0b9-6e3b8a8cda0b" />
			</EntityLinks>
		</Object>
		<Object EntityClass="ParticleEffect" Id="e6e33159-cc4c-4a57-aafc-9936b64fe205" Name="forge_particle_big" Pos="-0.8803711,0.2774658,0.7615356" Rotate="0.7071069,0.7071067,0,0" Scale="0.74,0.74,0.74" Type="ParticleEntity">
			<Properties bActive="0" ParticleEffect="professions.blacksmith.forge_fire_big" />
		</Object>
		<Object EntityClass="ParticleEffect" Id="ea482467-3c1d-4e86-a66c-9206a82d8cdb" Name="professions.blacksmith.burning_iron2" Pos="4.647343,-1.819687,0.4750862" Rotate="0.3420202,0,0,0.9396926" Type="ParticleEntity">
			<Properties bActive="0" bPrime="0" ParticleEffect="professions.blacksmith.burning_iron" />
		</Object>
		<Object EntityClass="Shop" Id="f48b243b-dc66-4101-be77-d5d7cb357a45" Name="Shop4" Pos="-1.091751,-1.074097,0" Type="Entity">
			<Properties iShopId="170" />
			<EntityLinks>
				<Link DebugTargetName="outPort_door" Name="shopDoor" TargetId="fda09b77-7f34-465b-bc60-1297c13dee52" />
			</EntityLinks>
		</Object>
		<Object EntityClass="PrefabPort" Id="f8efbc6b-abc2-482a-aa37-c8fd522c0f44" Name="outPort_area" Pos="-1.591469,-1.106674,0" Type="Entity">
			<Properties esPrefabPort_Type="Out" />
		</Object>
		<Object EntityClass="PrefabPort" Id="f8fb5c7a-50af-4ae3-9f03-58163ab90f30" Name="InputPort" Pos="2.828739,-2.569565,0.2000008" Rotate="0.3420202,0,0,0.9396926" Type="Entity">
			<EntityLinks>
				<Link DebugTargetName="Smithery" TargetId="60aca2b1-6373-4fc5-a07b-11b71c5a49d0" />
			</EntityLinks>
		</Object>
		<Object EntityClass="PrefabPort" Id="fda09b77-7f34-465b-bc60-1297c13dee52" Name="outPort_door" Pos="-1.59277,-1.59024,0" Type="Entity">
			<Properties esPrefabPort_Type="Out" />
		</Object>
	</Objects>
	<NestedLinks>
		<Link Name="freeSpotForPlayer[&apos;use&apos;]" SourceDebugName="smartObjectHolder" SourceId="de2befbb-d562-4123-a0b9-6e3b8a8cda0b" SourcePath="" TargetDebugName="port_entity" TargetId="7af0d691-7c48-46ff-8a4c-e92281d97dc5" TargetPath="d3a040a4-4123-4894-bc4c-e0d23f47e9cb" />
		<Link Name="" SourceDebugName="Shop4" SourceId="f48b243b-dc66-4101-be77-d5d7cb357a45" SourcePath="" TargetDebugName="port_stashEntity" TargetId="630cccb2-7fa1-428c-bb44-1c39f38a0126" TargetPath="8f2558c6-e8a6-4fc4-a146-d4d1cb00ce5e" />
		<Link Name="_" SourceDebugName="hub_2" SourceId="1e0d791e-8398-41e2-9aac-1abec9c17d6d" SourcePath="" TargetDebugName="port_use" TargetId="cdd47e3f-966a-4f86-8705-6555328e1708" TargetPath="d3a040a4-4123-4894-bc4c-e0d23f47e9cb" />
	</NestedLinks>
</Prefab>